gars_field/__init__.py
gars_field/edgarsgrid.py
gars_field/field.py
gars_field/garsgrid.py
gars_field/gedgarsgrid.py
gars_field/py.typed
gars_field-0.3.3.dist-info/LICENSE
gars_field-0.3.3.dist-info/METADATA
gars_field-0.3.3.dist-info/WHEEL
gars_field-0.3.3.dist-info/top_level.txt
gars_field-0.3.3.dist-info/RECORD
