Metadata-Version: 2.1
Name: gars-field
Version: 0.3.3
Summary: Toolkit to generate Global Area Reference System grids.
Home-page: https://github.com/corteva/gars-field
Download-URL: http://python.org/pypi/gars-field
Author: gars-field Contributors
License: BSD License
Project-URL: Documentation, https://github.com/corteva/gars-field
Project-URL: Release Notes, https://github.com/corteva/gars-field/releases
Project-URL: Bug Tracker, https://github.com/corteva/gars-field/issues
Project-URL: Source Code, https://github.com/corteva/gars-field
Keywords: GARS,grid
Platform: any
Classifier: Development Status :: 2 - Pre-Alpha
Classifier: Intended Audience :: Developers
Classifier: Natural Language :: English
Classifier: License :: OSI Approved :: BSD License
Classifier: Operating System :: OS Independent
Classifier: Programming Language :: Python
Classifier: Programming Language :: Python :: 3.8
Classifier: Programming Language :: Python :: 3.9
Classifier: Programming Language :: Python :: 3.10
Classifier: Programming Language :: Python :: 3.11
Classifier: Programming Language :: Python :: 3
Classifier: Topic :: Software Development :: Libraries :: Python Modules
Classifier: Topic :: Scientific/Engineering :: GIS
Requires-Python: >=3.8
License-File: LICENSE
Requires-Dist: shapely
Requires-Dist: pyproj (>=3.0.0)
Provides-Extra: all
Requires-Dist: pytest-cov ; extra == 'all'
Provides-Extra: dev
Requires-Dist: pytest-cov ; extra == 'dev'
